{
  "formatVersion": 1,
  "database": {
    "version": 2,
    "identityHash": "c88f6a7e8356d4d77b807c5f08935602",
    "entities": [
      {
        "ftsVersion": "FTS4",
        "ftsOptions": {
          "tokenizer": "simple",
          "tokenizerArgs": [],
          "contentTable": "",
          "languageIdColumnName": "",
          "matchInfo": "FTS4",
          "notIndexedColumns": [],
          "prefixSizes": [],
          "preferredOrder": "ASC"
        },
        "contentSyncTriggers": [],
        "tableName": "build_info_table",
        "createSql": "CREATE VIRTUAL TABLE IF NOT EXISTS `${TABLE_NAME}` USING FTS4(`version` TEXT NOT NULL, `date` INTEGER NOT NULL, `url` TEXT NOT NULL, `file_name` TEXT NOT NULL, `file_size` INTEGER NOT NULL, `sha` TEXT NOT NULL)",
        "fields": [
          {
            "fieldPath": "version",
            "columnName": "version",
            "affinity": "TEXT",
            "notNull": true
          },
          {
            "fieldPath": "date",
            "columnName": "date",
            "affinity": "INTEGER",
            "notNull": true
          },
          {
            "fieldPath": "url",
            "columnName": "url",
            "affinity": "TEXT",
            "notNull": true
          },
          {
            "fieldPath": "fileName",
            "columnName": "file_name",
            "affinity": "TEXT",
            "notNull": true
          },
          {
            "fieldPath": "fileSize",
            "columnName": "file_size",
            "affinity": "INTEGER",
            "notNull": true
          },
          {
            "fieldPath": "sha512",
            "columnName": "sha",
            "affinity": "TEXT",
            "notNull": true
          }
        ],
        "primaryKey": {
          "columnNames": [],
          "autoGenerate": false
        },
        "indices": [],
        "foreignKeys": []
      },
      {
        "ftsVersion": "FTS4",
        "ftsOptions": {
          "tokenizer": "simple",
          "tokenizerArgs": [],
          "contentTable": "",
          "languageIdColumnName": "",
          "matchInfo": "FTS4",
          "notIndexedColumns": [],
          "prefixSizes": [],
          "preferredOrder": "ASC"
        },
        "contentSyncTriggers": [],
        "tableName": "saved_state_table",
        "createSql": "CREATE VIRTUAL TABLE IF NOT EXISTS `${TABLE_NAME}` USING FTS4(`last_checked_time` INTEGER NOT NULL, `download_finished` INTEGER NOT NULL)",
        "fields": [
          {
            "fieldPath": "lastCheckedTime",
            "columnName": "last_checked_time",
            "affinity": "INTEGER",
            "notNull": true
          },
          {
            "fieldPath": "downloadFinished",
            "columnName": "download_finished",
            "affinity": "INTEGER",
            "notNull": true
          }
        ],
        "primaryKey": {
          "columnNames": [],
          "autoGenerate": false
        },
        "indices": [],
        "foreignKeys": []
      },
      {
        "ftsVersion": "FTS4",
        "ftsOptions": {
          "tokenizer": "simple",
          "tokenizerArgs": [],
          "contentTable": "",
          "languageIdColumnName": "",
          "matchInfo": "FTS4",
          "notIndexedColumns": [],
          "prefixSizes": [],
          "preferredOrder": "ASC"
        },
        "contentSyncTriggers": [],
        "tableName": "changelog_table",
        "createSql": "CREATE VIRTUAL TABLE IF NOT EXISTS `${TABLE_NAME}` USING FTS4(`date` INTEGER NOT NULL, `changelog` TEXT)",
        "fields": [
          {
            "fieldPath": "date",
            "columnName": "date",
            "affinity": "INTEGER",
            "notNull": true
          },
          {
            "fieldPath": "changelog",
            "columnName": "changelog",
            "affinity": "TEXT",
            "notNull": false
          }
        ],
        "primaryKey": {
          "columnNames": [],
          "autoGenerate": false
        },
        "indices": [],
        "foreignKeys": []
      }
    ],
    "views": [],
    "setupQueries": [
      "CREATE TABLE IF NOT EXISTS room_master_table (id INTEGER PRIMARY KEY,identity_hash TEXT)",
      "INSERT OR REPLACE INTO room_master_table (id,identity_hash) VALUES(42, 'c88f6a7e8356d4d77b807c5f08935602')"
    ]
  }
}